{
  "publicPath": "/_nuxt/",
  "all": [
    "@vite/client",
    "entry.mjs",
    "components/Form/Textarea.vue?vue&type=style&index=0&scoped=true&lang.css",
    "pages/create.vue?vue&type=style&index=0&scoped=true&lang.css",
    "pages/index.vue?vue&type=style&index=0&scoped=true&lang.css",
    "pages/update/[id].vue?vue&type=style&index=0&scoped=true&lang.css",
    "pages/user/login.vue?vue&type=style&index=0&scoped=true&lang.css",
    "pages/user/register.vue?vue&type=style&index=0&scoped=true&lang.css",
    "node_modules/@nuxt/ui-templates/dist/templates/error-404.vue?vue&type=style&index=0&scoped=true&lang.css",
    "node_modules/@nuxt/ui-templates/dist/templates/error-500.vue?vue&type=style&index=0&scoped=true&lang.css",
    "node_modules/@nuxt/ui-templates/dist/templates/error-dev.vue?vue&type=style&index=0&scoped=true&lang.css",
    "components/Nav.vue?vue&type=style&index=0&scoped=true&lang.css",
    "layouts/default.vue?vue&type=style&index=0&lang.css"
  ],
  "initial": [
    "@vite/client",
    "entry.mjs",
    "components/Form/Textarea.vue?vue&type=style&index=0&scoped=true&lang.css",
    "pages/create.vue?vue&type=style&index=0&scoped=true&lang.css",
    "pages/index.vue?vue&type=style&index=0&scoped=true&lang.css",
    "pages/update/[id].vue?vue&type=style&index=0&scoped=true&lang.css",
    "pages/user/login.vue?vue&type=style&index=0&scoped=true&lang.css",
    "pages/user/register.vue?vue&type=style&index=0&scoped=true&lang.css",
    "node_modules/@nuxt/ui-templates/dist/templates/error-404.vue?vue&type=style&index=0&scoped=true&lang.css",
    "node_modules/@nuxt/ui-templates/dist/templates/error-500.vue?vue&type=style&index=0&scoped=true&lang.css",
    "node_modules/@nuxt/ui-templates/dist/templates/error-dev.vue?vue&type=style&index=0&scoped=true&lang.css",
    "components/Nav.vue?vue&type=style&index=0&scoped=true&lang.css",
    "layouts/default.vue?vue&type=style&index=0&lang.css"
  ],
  "async": [],
  "modules": {}
}